[
	{
		"inputs": [
			{
				"internalType": "uint256",
				"name": "_stakingId",
				"type": "uint256"
			}
		],
		"name": "claimEarnedReward",
		"outputs": [],
		"stateMutability": "nonpayable",
		"type": "function"
	},
	{
		"inputs": [
			{
				"internalType": "address",
				"name": "_dsdcToken",
				"type": "address"
			},
			{
				"internalType": "address",
				"name": "_mutantsToken",
				"type": "address"
			},
			{
				"internalType": "address",
				"name": "_stonedToken",
				"type": "address"
			},
			{
				"internalType": "address",
				"name": "_rewardToken",
				"type": "address"
			}
		],
		"stateMutability": "nonpayable",
		"type": "constructor"
	},
	{
		"anonymous": false,
		"inputs": [
			{
				"indexed": true,
				"internalType": "address",
				"name": "previousOwner",
				"type": "address"
			},
			{
				"indexed": true,
				"internalType": "address",
				"name": "newOwner",
				"type": "address"
			}
		],
		"name": "OwnershipTransferred",
		"type": "event"
	},
	{
		"inputs": [
			{
				"internalType": "address",
				"name": "_token",
				"type": "address"
			}
		],
		"name": "recoverToken",
		"outputs": [],
		"stateMutability": "nonpayable",
		"type": "function"
	},
	{
		"inputs": [],
		"name": "renounceOwnership",
		"outputs": [],
		"stateMutability": "nonpayable",
		"type": "function"
	},
	{
		"inputs": [
			{
				"internalType": "uint256",
				"name": "_stakingId",
				"type": "uint256"
			},
			{
				"internalType": "uint256",
				"name": "_percent",
				"type": "uint256"
			}
		],
		"name": "setAPR",
		"outputs": [],
		"stateMutability": "nonpayable",
		"type": "function"
	},
	{
		"inputs": [
			{
				"internalType": "uint256",
				"name": "_stakingId",
				"type": "uint256"
			},
			{
				"internalType": "bool",
				"name": "_conclude",
				"type": "bool"
			}
		],
		"name": "setStakeConclude",
		"outputs": [],
		"stateMutability": "nonpayable",
		"type": "function"
	},
	{
		"inputs": [
			{
				"internalType": "uint256",
				"name": "_stakingId",
				"type": "uint256"
			},
			{
				"internalType": "uint256[]",
				"name": "tokenIds",
				"type": "uint256[]"
			}
		],
		"name": "stake",
		"outputs": [],
		"stateMutability": "nonpayable",
		"type": "function"
	},
	{
		"inputs": [
			{
				"internalType": "address",
				"name": "newOwner",
				"type": "address"
			}
		],
		"name": "transferOwnership",
		"outputs": [],
		"stateMutability": "nonpayable",
		"type": "function"
	},
	{
		"inputs": [
			{
				"internalType": "uint256",
				"name": "_stakingId",
				"type": "uint256"
			},
			{
				"internalType": "uint256[]",
				"name": "tokenIds",
				"type": "uint256[]"
			}
		],
		"name": "unstake",
		"outputs": [],
		"stateMutability": "nonpayable",
		"type": "function"
	},
	{
		"inputs": [
			{
				"internalType": "uint256",
				"name": "_stakingId",
				"type": "uint256"
			},
			{
				"internalType": "address",
				"name": "_account",
				"type": "address"
			}
		],
		"name": "getEarnedRewards",
		"outputs": [
			{
				"internalType": "uint256",
				"name": "",
				"type": "uint256"
			}
		],
		"stateMutability": "view",
		"type": "function"
	},
	{
		"inputs": [
			{
				"internalType": "uint256",
				"name": "_stakingId",
				"type": "uint256"
			},
			{
				"internalType": "address",
				"name": "_account",
				"type": "address"
			}
		],
		"name": "getStakedTokens",
		"outputs": [
			{
				"internalType": "uint256[]",
				"name": "",
				"type": "uint256[]"
			}
		],
		"stateMutability": "view",
		"type": "function"
	},
	{
		"inputs": [
			{
				"internalType": "uint256",
				"name": "_stakingId",
				"type": "uint256"
			},
			{
				"internalType": "address",
				"name": "_account",
				"type": "address"
			},
			{
				"internalType": "uint256",
				"name": "_tokenId",
				"type": "uint256"
			}
		],
		"name": "getTokenEndStake",
		"outputs": [
			{
				"internalType": "uint256",
				"name": "",
				"type": "uint256"
			}
		],
		"stateMutability": "view",
		"type": "function"
	},
	{
		"inputs": [],
		"name": "minAPR",
		"outputs": [
			{
				"internalType": "uint16",
				"name": "",
				"type": "uint16"
			}
		],
		"stateMutability": "view",
		"type": "function"
	},
	{
		"inputs": [],
		"name": "owner",
		"outputs": [
			{
				"internalType": "address",
				"name": "",
				"type": "address"
			}
		],
		"stateMutability": "view",
		"type": "function"
	},
	{
		"inputs": [
			{
				"internalType": "uint256",
				"name": "",
				"type": "uint256"
			}
		],
		"name": "plans",
		"outputs": [
			{
				"internalType": "uint256",
				"name": "apr",
				"type": "uint256"
			},
			{
				"internalType": "uint256",
				"name": "stakeDuration",
				"type": "uint256"
			},
			{
				"internalType": "address",
				"name": "stakingToken",
				"type": "address"
			},
			{
				"internalType": "bool",
				"name": "conclude",
				"type": "bool"
			}
		],
		"stateMutability": "view",
		"type": "function"
	},
	{
		"inputs": [],
		"name": "rewardToken",
		"outputs": [
			{
				"internalType": "address",
				"name": "",
				"type": "address"
			}
		],
		"stateMutability": "view",
		"type": "function"
	}
]